ncuphy/__init__.py
ncuphy/experiment/__init__.py
ncuphy/experiment/ads1115/__init__.py
ncuphy/experiment/ads1115/read.py
ncuphy/experiment/example/__init__.py
ncuphy/experiment/mpu6050/__init__.py
ncuphy/experiment/mpu6050/read.py
ncuphy/experiment/mpu9250/__init__.py
ncuphy/experiment/mpu9250/read.py
ncuphy/experiment/stepper_motor/__init__.py
ncuphy/experiment/stepper_motor/backup.py
ncuphy/experiment/stepper_motor/control.py
ncuphy/highschool/__init__.py
ncuphy/highschool/library.py
ncuphy/highschool/ncugrovepi.py
ncuphy/highschool/exp1/__init__.py
ncuphy/highschool/exp1/planks_constant.py
ncuphy/highschool/exp2/__init__.py
ncuphy/highschool/exp2/light_intensity.py
ncuphy/highschool/exp3/__init__.py
ncuphy/highschool/exp3/light_polarization.py
ncuphy-0.1.25.dist-info/LICENSE
ncuphy-0.1.25.dist-info/METADATA
ncuphy-0.1.25.dist-info/WHEEL
ncuphy-0.1.25.dist-info/top_level.txt
ncuphy-0.1.25.dist-info/RECORD
